pgnanki/__init__.py
pgnanki-1.0.7.dist-info/WHEEL
pgnanki-1.0.7.dist-info/METADATA
pgnanki-1.0.7.dist-info/RECORD
