Metadata-Version: 2.3
Name: pgnanki
Version: 1.0.7
Summary: Making Anki notes of type Chess 2.0 for one color's positions in a PGN.
Keywords: anki,chess,pgn
Author: John Dawson
Author-email: John Dawson <john.a.dawson@proton.me>
License:                     GNU GENERAL PUBLIC LICENSE
Requires-Dist: chess
Maintainer: John Dawson
Maintainer-email: John Dawson <john.a.dawson@proton.me>
Project-URL: Documentation, https://github.com/JohnADawson/pgnanki/blob/master/src/pgnanki/__init__.py
Project-URL: Homepage, https://github.com/JohnADawson/pgnanki
